Metadata-Version: 2.1
Name: rp-annot
Version: 0.0.2
Summary: Minimal compression library for sparse or contiguous 1D numpy boolean arrays
Home-page: https://github.com/Abe404/rp_annot
Author: Abraham George Smith
Author-email: abe@abesmith.co.uk
License: GPLv3
Download-URL: https://github.com/Abe404/rp_annot/archive/refs/tags/0.0.2.tar.gz
Keywords: numpy,compression,sparse,boolean
Platform: UNKNOWN
Classifier: Intended Audience :: Developers
Classifier: Programming Language :: Python :: 3
Classifier: License :: OSI Approved :: GNU General Public License v3 (GPLv3)
Classifier: Operating System :: OS Independent
